egi_telemetry/__init__.py
egi_telemetry/cli.py
egi_telemetry/client.py
egi_telemetry/config.py
egi_telemetry/fastapi_middleware.py
egi_telemetry-0.1.0.dist-info/METADATA
egi_telemetry-0.1.0.dist-info/WHEEL
egi_telemetry-0.1.0.dist-info/entry_points.txt
egi_telemetry-0.1.0.dist-info/RECORD
