Metadata-Version: 2.4
Name: egi-telemetry
Version: 0.1.0
Summary: Telemetry SDK for EGIntegrations client engines
Author: EGIntegrations
License: Proprietary
Requires-Python: >=3.9
Requires-Dist: anyio>=4.0
Requires-Dist: httpx>=0.27
Requires-Dist: pydantic>=2.6
Provides-Extra: fastapi
Requires-Dist: fastapi>=0.111; extra == 'fastapi'
